rtl/data_memory.v
// data_memory.v
`timescale 1ns/1ps
module data_memory(
    input clk,
    input mem_write,
    input mem_read,
    input [31:0] addr,
    input [31:0] write_data,
    output reg [31:0] read_data
);
    reg [31:0] mem [0:255];
    integer i;
    initial begin
        for (i=0;i<256;i=i+1) mem[i]=0;
    end

    always @(posedge clk) begin
        if (mem_write) mem[addr[9:2]] <= write_data;
    end

    always @(*) begin
        if (mem_read) read_data = mem[addr[9:2]];
        else read_data = 32'd0;
    end
    // testbench can initialize mem[] hierarchically
endmodule

rtl/alu.v
// alu.v
`timescale 1ns/1ps
module alu(
    input  [31:0] a,
    input  [31:0] b,
    input  [3:0]  alu_ctrl,
    output reg [31:0] result,
    output zero
);
    assign zero = (result == 32'd0);
    always @(*) begin
        case (alu_ctrl)
            4'h0: result = a + b;          // ADD
            4'h1: result = a - b;          // SUB
            4'h2: result = a & b;          // AND
            4'h3: result = a | b;          // OR
            4'h4: result = (a < b) ? 32'd1 : 32'd0; // SLT
            4'h5: result = a ^ b;          // XOR
            default: result = 32'd0;
        endcase
    end
endmodule

rtl/hazard_unit.v
// hazard_unit.v
`timescale 1ns/1ps
module hazard_unit(
    input id_ex_memread,
    input [4:0] id_ex_rt,
    input [4:0] if_id_rs,
    input [4:0] if_id_rt,
    output reg pc_write,
    output reg if_id_write,
    output reg control_stall
);
    // If next instr depends on a load in EX stage -> stall one cycle
    always @(*) begin
        pc_write = 1;
        if_id_write = 1;
        control_stall = 0;
        if (id_ex_memread && ( (id_ex_rt == if_id_rs) || (id_ex_rt == if_id_rt) )) begin
            // stall
            pc_write = 0;
            if_id_write = 0;
            control_stall = 1; // zero control signals in ID/EX
        end
    end
endmodule

rtl/forwarding_unit.v
// forwarding_unit.v
`timescale 1ns/1ps
module forwarding_unit(
    input [4:0] id_ex_rs, id_ex_rt,
    input [4:0] ex_mem_rd,
    input ex_mem_regwrite,
    input [4:0] mem_wb_rd,
    input mem_wb_regwrite,
    output reg [1:0] forwardA,
    output reg [1:0] forwardB
);
    // 00 = from regfile, 10 = from EX/MEM (ALU result), 01 = from MEM/WB
    always @(*) begin
        forwardA = 2'b00;
        forwardB = 2'b00;
        // EX hazard
        if (ex_mem_regwrite && (ex_mem_rd != 0) && (ex_mem_rd == id_ex_rs)) forwardA = 2'b10;
        if (ex_mem_regwrite && (ex_mem_rd != 0) && (ex_mem_rd == id_ex_rt)) forwardB = 2'b10;
        // MEM hazard (lower priority)
        if (mem_wb_regwrite && (mem_wb_rd != 0) && (mem_wb_rd == id_ex_rs) && !(ex_mem_regwrite && (ex_mem_rd !=0) && (ex_mem_rd == id_ex_rs))) forwardA = 2'b01;
        if (mem_wb_regwrite && (mem_wb_rd != 0) && (mem_wb_rd == id_ex_rt) && !(ex_mem_regwrite && (ex_mem_rd !=0) && (ex_mem_rd == id_ex_rt))) forwardB = 2'b01;
    end
endmodule

rtl/control_unit.v
// control_unit.v
`timescale 1ns/1ps
module control_unit(
    input [5:0] opcode,
    input [5:0] funct,
    output reg reg_write,
    output reg alu_src,    // 0 -> reg, 1 -> imm
    output reg mem_read,
    output reg mem_write,
    output reg mem_to_reg, // 1 -> load, 0 -> ALU
    output reg branch,
    output reg [3:0] alu_op
);
    // Opcodes (simple MIPS-like):
    localparam RTYPE = 6'd0;
    localparam LW    = 6'd35; // 100011
    localparam SW    = 6'd43; // 101011
    localparam BEQ   = 6'd4;  // 000100
    localparam ADDI  = 6'd8;  // 001000

    always @(*) begin
        // defaults
        reg_write = 0; alu_src = 0; mem_read = 0; mem_write = 0;
        mem_to_reg = 0; branch = 0; alu_op = 4'h0;

        case (opcode)
            RTYPE: begin
                reg_write = 1;
                alu_src = 0;
                mem_read = 0; mem_write = 0;
                mem_to_reg = 0;
                branch = 0;
                // decode funct for alu_op
                case(funct)
                    6'h20: alu_op = 4'h0; // add
                    6'h22: alu_op = 4'h1; // sub
                    6'h24: alu_op = 4'h2; // and
                    6'h25: alu_op = 4'h3; // or
                    6'h2A: alu_op = 4'h4; // slt
                    6'h26: alu_op = 4'h5; // xor
                    default: alu_op = 4'h0;
                endcase
            end
            LW: begin
                reg_write = 1;
                alu_src = 1;
                mem_read = 1;
                mem_write = 0;
                mem_to_reg = 1;
                branch = 0;
                alu_op = 4'h0; // add for address calc
            end
            SW: begin
                reg_write = 0;
                alu_src = 1;
                mem_read = 0;
                mem_write = 1;
                mem_to_reg = 0;
                branch = 0;
                alu_op = 4'h0;
            end
            BEQ: begin
                reg_write = 0;
                alu_src = 0;
                mem_read = 0;
                mem_write = 0;
                mem_to_reg = 0;
                branch = 1;
                alu_op = 4'h1; // sub for comparing
            end
            ADDI: begin
                reg_write = 1;
                alu_src = 1;
                mem_read = 0;
                mem_write = 0;
                mem_to_reg = 0;
                branch = 0;
                alu_op = 4'h0; // add
            end
            default: begin
            end
        endcase
    end
endmodule

rtl/reg_file.v
// reg_file.v
`timescale 1ns/1ps
module reg_file(
    input clk,
    input we,
    input [4:0] rd_addr,
    input [31:0] rd_data,
    input [4:0] rs1_addr,
    input [4:0] rs2_addr,
    output [31:0] rs1_data,
    output [31:0] rs2_data
);
    reg [31:0] regs [0:31];
    integer i;
    initial begin
        for (i=0;i<32;i=i+1) regs[i]=0;
    end

    assign rs1_data = (rs1_addr==0) ? 32'd0 : regs[rs1_addr];
    assign rs2_data = (rs2_addr==0) ? 32'd0 : regs[rs2_addr];

    always @(posedge clk) begin
        if (we && rd_addr != 0) begin
            regs[rd_addr] <= rd_data;
        end
    end

    // helper for testbench reading
    function [31:0] read_reg;
        input [4:0] idx;
        begin
            read_reg = regs[idx];
        end
    endfunction
endmodule

rtl/instr_memory.v
// instr_memory.v
`timescale 1ns/1ps
module instr_memory(
    input [31:0] pc,
    output [31:0] instr
);
    reg [31:0] mem [0:255];
    initial begin
        // default zero; testbench will overwrite contents or we can keep default sample
        // testbench writes instructions directly by poking mem[] via hierarchical reference
    end
    assign instr = mem[pc[9:2]]; // word aligned index
    // allow testbench to poke mem via hierarchical name
endmodule

rtl/cpu_top.v
// cpu_top.v
`timescale 1ns/1ps
module cpu_top(
    input clk,
    input rst
);
    // Program Counter
    reg [31:0] pc;
    wire [31:0] instr;
    wire [31:0] pc_plus4 = pc + 4;

    instr_memory imem(.pc(pc), .instr(instr));
    // instantiate regfile
    wire [31:0] rf_rs1, rf_rs2;
    reg [4:0] rf_rd_addr;
    reg [31:0] rf_rd_data;
    reg rf_we;

    reg_file rf(.clk(clk), .we(rf_we), .rd_addr(rf_rd_addr), .rd_data(rf_rd_data),
                .rs1_addr(id_rs1_addr), .rs2_addr(id_rs2_addr),
                .rs1_data(rf_rs1), .rs2_data(rf_rs2));

    // control signals produced in ID stage
    wire cu_reg_write, cu_alu_src, cu_mem_read, cu_mem_write, cu_mem_to_reg, cu_branch;
    wire [3:0] cu_alu_op;

    // decode fields in ID stage
    wire [5:0] id_opcode = if_id_instr[31:26];
    wire [4:0] id_rs     = if_id_instr[25:21];
    wire [4:0] id_rt     = if_id_instr[20:16];
    wire [4:0] id_rd     = if_id_instr[15:11];
    wire [5:0] id_funct  = if_id_instr[5:0];
    wire [15:0] id_imm16 = if_id_instr[15:0];
    wire [31:0] id_imm   = {{16{id_imm16[15]}}, id_imm16};


    // control unit
    control_unit cu(.opcode(id_opcode), .funct(id_funct), .reg_write(cu_reg_write),
                    .alu_src(cu_alu_src), .mem_read(cu_mem_read), .mem_write(cu_mem_write),
                    .mem_to_reg(cu_mem_to_reg), .branch(cu_branch), .alu_op(cu_alu_op));

    // pipeline registers signals (IDs)
    // IF/ID
    reg [31:0] if_id_pc4;
    reg [31:0] if_id_instr;
    // ID/EX
    reg [31:0] id_ex_pc4, id_ex_rs1_val, id_ex_rs2_val, id_ex_imm;
    reg [4:0] id_ex_rs1_addr_wire, id_ex_rs2_addr_wire, id_ex_rd_addr_wire;
    reg id_ex_regwrite, id_ex_alu_src, id_ex_mem_read, id_ex_mem_write, id_ex_mem_to_reg, id_ex_branch;
    reg [3:0] id_ex_alu_op;

    // EX/MEM
    reg [31:0] ex_mem_alu_result, ex_mem_write_data;
    reg [4:0] ex_mem_rd;
    reg ex_mem_regwrite, ex_mem_mem_read, ex_mem_mem_write, ex_mem_mem_to_reg, ex_mem_branch;

    // MEM/WB
    reg [31:0] mem_wb_read_data, mem_wb_alu_result;
    reg [4:0] mem_wb_rd;
    reg mem_wb_regwrite, mem_wb_mem_to_reg;

    // forwarding unit
    wire [1:0] forwardA, forwardB;
    forwarding_unit fwd(
        .id_ex_rs(id_ex_rs1_addr_wire), .id_ex_rt(id_ex_rs2_addr_wire),
        .ex_mem_rd(ex_mem_rd), .ex_mem_regwrite(ex_mem_regwrite),
        .mem_wb_rd(mem_wb_rd), .mem_wb_regwrite(mem_wb_regwrite),
        .forwardA(forwardA), .forwardB(forwardB)
    );

    // hazard unit
    wire pc_write, if_id_write, control_stall;
    hazard_unit hzd(.id_ex_memread(id_ex_mem_read), .id_ex_rt(id_ex_rs2_addr_wire),
                    .if_id_rs(if_id_instr[25:21]), .if_id_rt(if_id_instr[20:16]),
                    .pc_write(pc_write), .if_id_write(if_id_write), .control_stall(control_stall));

    // ALU wires
    reg [31:0] alu_a, alu_b;
    wire [31:0] alu_result;
    wire alu_zero;
    alu ALU(.a(alu_a), .b(alu_b), .alu_ctrl(id_ex_alu_op), .result(alu_result), .zero(alu_zero));

    // data memory
    wire [31:0] data_read;
    data_memory dmem(.clk(clk), .mem_write(ex_mem_mem_write), .mem_read(ex_mem_mem_read),
                     .addr(ex_mem_alu_result), .write_data(ex_mem_write_data), .read_data(data_read));

    // IF stage
    always @(posedge clk or posedge rst) begin
        if (rst) pc <= 0;
        else if (pc_write) begin
            pc <= pc_next;
        end
    end

    wire [31:0] pc_next;
    // branch decision from EX stage (we use ex stage info)
    wire ex_branch_taken = ex_mem_branch & (ex_mem_alu_result == 0); // for BEQ: alu_result zero -> equal
    assign pc_next = ex_branch_taken ? ex_mem_alu_result /*we store branch target in alu_result?*/ : pc_plus4;
    // Note: For simplicity we use branch target in ALU result. In production you'd add calculation.

    // instruction fetch registers
    always @(posedge clk or posedge rst) begin
        if (rst) begin
            if_id_pc4 <= 0; if_id_instr <= 0;
        end else begin
            if (if_id_write) begin
                if_id_pc4 <= pc_plus4;
                if_id_instr <= instr;
            end
        end
    end

    // ID stage: read register file
    wire [4:0] id_rs1_addr = if_id_instr[25:21];
    wire [4:0] id_rs2_addr = if_id_instr[20:16];
    reg [31:0] id_rs1_val, id_rs2_val;

    always @(*) begin
        id_rs1_val = rf_rs1;
        id_rs2_val = rf_rs2;
    end

    // ID/EX register update (on clk)
    always @(posedge clk or posedge rst) begin
        if (rst) begin
            id_ex_pc4 <=0; id_ex_rs1_val<=0; id_ex_rs2_val<=0; id_ex_imm<=0;
            id_ex_rs1_addr_wire<=0; id_ex_rs2_addr_wire<=0; id_ex_rd_addr_wire<=0;
            id_ex_regwrite<=0; id_ex_alu_src<=0; id_ex_mem_read<=0; id_ex_mem_write<=0; id_ex_mem_to_reg<=0; id_ex_branch<=0;
            id_ex_alu_op<=0;
        end else begin
            id_ex_pc4 <= if_id_pc4;
            id_ex_rs1_val <= id_rs1_val;
            id_ex_rs2_val <= id_rs2_val;
            id_ex_imm <= id_imm;
            id_ex_rs1_addr_wire <= id_rs1_addr;
            id_ex_rs2_addr_wire <= id_rs2_addr;
            id_ex_rd_addr_wire <= (id_opcode==6'd0) ? id_rd : id_rt; // R-type rd else I-type rt
            if (control_stall) begin
                id_ex_regwrite <= 0;
                id_ex_alu_src <= 0;
                id_ex_mem_read <= 0;
                id_ex_mem_write <= 0;
                id_ex_mem_to_reg <= 0;
                id_ex_branch <= 0;
                id_ex_alu_op <= 0;
            end else begin
                id_ex_regwrite <= cu_reg_write;
                id_ex_alu_src <= cu_alu_src;
                id_ex_mem_read <= cu_mem_read;
                id_ex_mem_write <= cu_mem_write;
                id_ex_mem_to_reg <= cu_mem_to_reg;
                id_ex_branch <= cu_branch;
                id_ex_alu_op <= cu_alu_op;
            end
        end
    end

    // EX stage: ALU inputs with forwarding
    reg [31:0] alu_input1, alu_input2;
    always @(*) begin
        // forwardA
        case (forwardA)
            2'b00: alu_input1 = id_ex_rs1_val;
            2'b10: alu_input1 = ex_mem_alu_result;
            2'b01: alu_input1 = mem_wb_regwrite ? (mem_wb_mem_to_reg ? mem_wb_read_data : mem_wb_alu_result) : 0;
            default: alu_input1 = id_ex_rs1_val;
        endcase

        // forwardB
        case (forwardB)
            2'b00: alu_input2 = id_ex_rs2_val;
            2'b10: alu_input2 = ex_mem_alu_result;
            2'b01: alu_input2 = mem_wb_regwrite ? (mem_wb_mem_to_reg ? mem_wb_read_data : mem_wb_alu_result) : 0;
            default: alu_input2 = id_ex_rs2_val;
        endcase

        alu_a = alu_input1;
        alu_b = id_ex_alu_src ? id_ex_imm : alu_input2;
    end

    // update EX/MEM pipeline register on clk
    always @(posedge clk or posedge rst) begin
        if (rst) begin
            ex_mem_alu_result <=0; ex_mem_write_data<=0; ex_mem_rd<=0;
            ex_mem_regwrite<=0; ex_mem_mem_read<=0; ex_mem_mem_write<=0; ex_mem_mem_to_reg<=0; ex_mem_branch<=0;
        end else begin
            ex_mem_alu_result <= alu_result;
            ex_mem_write_data <= alu_input2;
            ex_mem_rd <= id_ex_rd_addr_wire;
            ex_mem_regwrite <= id_ex_regwrite;
            ex_mem_mem_read <= id_ex_mem_read;
            ex_mem_mem_write <= id_ex_mem_write;
            ex_mem_mem_to_reg <= id_ex_mem_to_reg;
            ex_mem_branch <= id_ex_branch;
        end
    end

    // MEM stage -> perform load/store
    always @(posedge clk or posedge rst) begin
        if (rst) begin
            mem_wb_read_data <= 0; mem_wb_alu_result <= 0; mem_wb_rd <= 0; mem_wb_regwrite <=0; mem_wb_mem_to_reg<=0;
        end else begin
            // read_data provided by data_memory combinatorial read_data
            mem_wb_read_data <= data_read;
            mem_wb_alu_result <= ex_mem_alu_result;
            mem_wb_rd <= ex_mem_rd;
            mem_wb_regwrite <= ex_mem_regwrite;
            mem_wb_mem_to_reg <= ex_mem_mem_to_reg;
        end
    end

    // WB stage -> writeback to regfile
    always @(*) begin
        rf_we = mem_wb_regwrite;
        rf_rd_addr = mem_wb_rd;
        rf_rd_data = mem_wb_mem_to_reg ? mem_wb_read_data : mem_wb_alu_result;
    end

    // For testbench visibility, expose some signals via hierarchical refs (done in TB)
endmodule

tb/cpu_tb.v
// cpu_tb.v - self-checking testbench
`timescale 1ns/1ps


module cpu_tb;
    reg clk, rst;
    integer cycle;

    // instantiate cpu_top
    cpu_top DUT(.clk(clk), .rst(rst));

    // helper tasks to assemble MIPS-like instructions
    function [31:0] instr_r;
        input [5:0] funct;
        input [4:0] rs, rt, rd;
        begin
            instr_r = {6'd0, rs, rt, rd, 5'd0, funct};
        end
    endfunction

    function [31:0] instr_i;
        input [5:0] opcode;
        input [4:0] rs, rt;
        input [15:0] imm;
        begin
            instr_i = {opcode, rs, rt, imm};
        end
    endfunction

    initial begin
        // waveform dump
        $dumpfile("cpu_tb.vcd");
        $dumpvars(0,cpu_tb);

        // clock
        clk = 0; rst = 1;
        #20 rst = 0;

        // Initialize register file values via hierarchical access
        // rf is instantiated inside cpu_top as rf
        DUT.rf.regs[2] = 32'd10; // R2 = 10
        DUT.rf.regs[3] = 32'd20; // R3 = 20
        DUT.rf.regs[5] = 32'd5;  // R5 = 5

        // Initialize data memory at address 0 (word 0)
        DUT.dmem.mem[0] = 32'd100;

        // Load instructions into instruction memory mem[]
        // Program (addresses 0,4,...):
        // ADD R1, R2, R3    -> R1 = 10 + 20 = 30
        // ADD R4, R1, R5    -> R4 = 30 + 5 = 35 (requires forwarding)
        // LW  R6, 0(R0)     -> R6 = mem[0] = 100
        // ADD R7, R6, R5    -> R7 = 100 + 5 = 105 (load-use -> hazard)
        // BEQ R2, R3, +2    -> not taken
        // ADD R8, R2, R2    -> R8 = 10 + 10 = 20
        // SUB R9, R3, R5    -> R9 = 20 - 5 = 15

        DUT.imem.mem[0] = instr_r(6'h20, 5'd2, 5'd3, 5'd1); // ADD R1,R2,R3 (funct=32)
        DUT.imem.mem[1] = instr_r(6'h20, 5'd1, 5'd5, 5'd4); // ADD R4,R1,R5
        DUT.imem.mem[2] = instr_i(6'd35, 5'd0, 5'd6, 16'd0); // LW R6,0(R0)
        DUT.imem.mem[3] = instr_r(6'h20, 5'd6, 5'd5, 5'd7); // ADD R7,R6,R5
        DUT.imem.mem[4] = instr_i(6'd4, 5'd2, 5'd3, 16'd2); // BEQ R2,R3, +2 (skip next if equal)
        DUT.imem.mem[5] = instr_r(6'h20, 5'd2, 5'd2, 5'd8); // ADD R8,R2,R2
        DUT.imem.mem[6] = instr_r(6'h22, 5'd3, 5'd5, 5'd9); // SUB R9,R3,R5 (funct=34)

        // run for enough cycles
        for (cycle=0; cycle<120; cycle=cycle+1) begin
            #5 clk = ~clk;
            #5 clk = ~clk;
        end

        // check expected registers
        $display("R1=%0d, expected 30", DUT.rf.read_reg(5'd1));
        $display("R4=%0d, expected 35", DUT.rf.read_reg(5'd4));
        $display("R6=%0d, expected 100", DUT.rf.read_reg(5'd6));
        $display("R7=%0d, expected 105", DUT.rf.read_reg(5'd7));
        $display("R8=%0d, expected 20", DUT.rf.read_reg(5'd8));
        $display("R9=%0d, expected 15", DUT.rf.read_reg(5'd9));

        if (DUT.rf.read_reg(5'd1) == 30 && DUT.rf.read_reg(5'd4) == 35 &&
            DUT.rf.read_reg(5'd6) == 100 && DUT.rf.read_reg(5'd7) == 105 &&
            DUT.rf.read_reg(5'd8) == 20 && DUT.rf.read_reg(5'd9) == 15) begin
            $display("TEST PASSED");
        end else begin
            $display("TEST FAILED");
        end
        $finish;
    end
endmodule

cpu_tb.vcd
$date
	Sat Nov 15 22:06:34 2025
$end
$version
	Icarus Verilog
$end
$timescale
	1ps
$end
$scope module cpu_tb $end
$var reg 1 ! clk $end
$var reg 1 " rst $end
$var integer 32 # cycle [31:0] $end
$scope function instr_i $end
$var reg 16 $ imm [15:0] $end
$var reg 6 % opcode [5:0] $end
$var reg 5 & rs [4:0] $end
$var reg 5 ' rt [4:0] $end
$upscope $end
$scope function instr_r $end
$var reg 6 ( funct [5:0] $end
$var reg 5 ) rd [4:0] $end
$var reg 5 * rs [4:0] $end
$var reg 5 + rt [4:0] $end
$upscope $end
$scope module DUT $end
$var wire 1 ! clk $end
$var wire 1 , ex_branch_taken $end
$var wire 1 " rst $end
$var wire 32 - rf_rs2 [31:0] $end
$var wire 32 . rf_rs1 [31:0] $end
$var wire 1 / pc_write $end
$var wire 32 0 pc_plus4 [31:0] $end
$var wire 32 1 pc_next [31:0] $end
$var wire 32 2 instr [31:0] $end
$var wire 1 3 if_id_write $end
$var wire 5 4 id_rt [4:0] $end
$var wire 5 5 id_rs2_addr [4:0] $end
$var wire 5 6 id_rs1_addr [4:0] $end
$var wire 5 7 id_rs [4:0] $end
$var wire 5 8 id_rd [4:0] $end
$var wire 6 9 id_opcode [5:0] $end
$var wire 16 : id_imm16 [15:0] $end
$var wire 32 ; id_imm [31:0] $end
$var wire 6 < id_funct [5:0] $end
$var wire 2 = forwardB [1:0] $end
$var wire 2 > forwardA [1:0] $end
$var wire 32 ? data_read [31:0] $end
$var wire 1 @ cu_reg_write $end
$var wire 1 A cu_mem_write $end
$var wire 1 B cu_mem_to_reg $end
$var wire 1 C cu_mem_read $end
$var wire 1 D cu_branch $end
$var wire 1 E cu_alu_src $end
$var wire 4 F cu_alu_op [3:0] $end
$var wire 1 G control_stall $end
$var wire 1 H alu_zero $end
$var wire 32 I alu_result [31:0] $end
$var reg 32 J alu_a [31:0] $end
$var reg 32 K alu_b [31:0] $end
$var reg 32 L alu_input1 [31:0] $end
$var reg 32 M alu_input2 [31:0] $end
$var reg 32 N ex_mem_alu_result [31:0] $end
$var reg 1 O ex_mem_branch $end
$var reg 1 P ex_mem_mem_read $end
$var reg 1 Q ex_mem_mem_to_reg $end
$var reg 1 R ex_mem_mem_write $end
$var reg 5 S ex_mem_rd [4:0] $end
$var reg 1 T ex_mem_regwrite $end
$var reg 32 U ex_mem_write_data [31:0] $end
$var reg 4 V id_ex_alu_op [3:0] $end
$var reg 1 W id_ex_alu_src $end
$var reg 1 X id_ex_branch $end
$var reg 32 Y id_ex_imm [31:0] $end
$var reg 1 Z id_ex_mem_read $end
$var reg 1 [ id_ex_mem_to_reg $end
$var reg 1 \ id_ex_mem_write $end
$var reg 32 ] id_ex_pc4 [31:0] $end
$var reg 5 ^ id_ex_rd_addr_wire [4:0] $end
$var reg 1 _ id_ex_regwrite $end
$var reg 5 ` id_ex_rs1_addr_wire [4:0] $end
$var reg 32 a id_ex_rs1_val [31:0] $end
$var reg 5 b id_ex_rs2_addr_wire [4:0] $end
$var reg 32 c id_ex_rs2_val [31:0] $end
$var reg 32 d id_rs1_val [31:0] $end
$var reg 32 e id_rs2_val [31:0] $end
$var reg 32 f if_id_instr [31:0] $end
$var reg 32 g if_id_pc4 [31:0] $end
$var reg 32 h mem_wb_alu_result [31:0] $end
$var reg 1 i mem_wb_mem_to_reg $end
$var reg 5 j mem_wb_rd [4:0] $end
$var reg 32 k mem_wb_read_data [31:0] $end
$var reg 1 l mem_wb_regwrite $end
$var reg 32 m pc [31:0] $end
$var reg 5 n rf_rd_addr [4:0] $end
$var reg 32 o rf_rd_data [31:0] $end
$var reg 1 p rf_we $end
$scope module ALU $end
$var wire 32 q a [31:0] $end
$var wire 4 r alu_ctrl [3:0] $end
$var wire 32 s b [31:0] $end
$var wire 1 H zero $end
$var reg 32 t result [31:0] $end
$upscope $end
$scope module cu $end
$var wire 6 u funct [5:0] $end
$var wire 6 v opcode [5:0] $end
$var parameter 6 w ADDI $end
$var parameter 6 x BEQ $end
$var parameter 6 y LW $end
$var parameter 6 z RTYPE $end
$var parameter 6 { SW $end
$var reg 4 | alu_op [3:0] $end
$var reg 1 E alu_src $end
$var reg 1 D branch $end
$var reg 1 C mem_read $end
$var reg 1 B mem_to_reg $end
$var reg 1 A mem_write $end
$var reg 1 @ reg_write $end
$upscope $end
$scope module dmem $end
$var wire 32 } addr [31:0] $end
$var wire 1 ! clk $end
$var wire 1 P mem_read $end
$var wire 1 R mem_write $end
$var wire 32 ~ write_data [31:0] $end
$var reg 32 !" read_data [31:0] $end
$var integer 32 "" i [31:0] $end
$upscope $end
$scope module fwd $end
$var wire 5 #" ex_mem_rd [4:0] $end
$var wire 1 T ex_mem_regwrite $end
$var wire 5 $" id_ex_rs [4:0] $end
$var wire 5 %" id_ex_rt [4:0] $end
$var wire 5 &" mem_wb_rd [4:0] $end
$var wire 1 l mem_wb_regwrite $end
$var reg 2 '" forwardA [1:0] $end
$var reg 2 (" forwardB [1:0] $end
$upscope $end
$scope module hzd $end
$var wire 1 Z id_ex_memread $end
$var wire 5 )" id_ex_rt [4:0] $end
$var wire 5 *" if_id_rs [4:0] $end
$var wire 5 +" if_id_rt [4:0] $end
$var reg 1 G control_stall $end
$var reg 1 3 if_id_write $end
$var reg 1 / pc_write $end
$upscope $end
$scope module imem $end
$var wire 32 ," instr [31:0] $end
$var wire 32 -" pc [31:0] $end
$upscope $end
$scope module rf $end
$var wire 1 ! clk $end
$var wire 5 ." rd_addr [4:0] $end
$var wire 32 /" rd_data [31:0] $end
$var wire 5 0" rs1_addr [4:0] $end
$var wire 5 1" rs2_addr [4:0] $end
$var wire 1 p we $end
$var wire 32 2" rs2_data [31:0] $end
$var wire 32 3" rs1_data [31:0] $end
$var integer 32 4" i [31:0] $end
$scope function read_reg $end
$var reg 5 5" idx [4:0] $end
$upscope $end
$upscope $end
$upscope $end
$upscope $end
$enddefinitions $end
$comment Show the parameter values. $end
$dumpall
b101011 {
b0 z
b100011 y
b100 x
b1000 w
$end
#0
$dumpvars
bx 5"
b100000 4"
b0 3"
b0 2"
b0 1"
b0 0"
b0 /"
b0 ."
b0 -"
bx ,"
b0 +"
b0 *"
b0 )"
b0 ("
b0 '"
b0 &"
b0 %"
b0 $"
b0 #"
b100000000 ""
b0 !"
b0 ~
b0 }
b0 |
b0 v
b0 u
b0 t
b0 s
b0 r
b0 q
0p
b0 o
b0 n
b0 m
0l
b0 k
b0 j
0i
b0 h
b0 g
b0 f
b0 e
b0 d
b0 c
b0 b
b0 a
b0 `
0_
b0 ^
b0 ]
0\
0[
0Z
b0 Y
0X
0W
b0 V
b0 U
0T
b0 S
0R
0Q
0P
0O
b0 N
b0 M
b0 L
b0 K
b0 J
b0 I
1H
0G
b0 F
0E
0D
0C
0B
0A
1@
b0 ?
b0 >
b0 =
b0 <
b0 ;
b0 :
b0 9
b0 8
b0 7
b0 6
b0 5
b0 4
13
bx 2
b100 1
b100 0
1/
b0 .
b0 -
0,
bx +
bx *
bx )
bx (
bx '
bx &
bx %
bx $
bx #
1"
0!
$end
#20000
b0 #
b100 %
b10 &
b11 '
b10 $
b10000110000100000100000 2
b10000110000100000100000 ,"
b100010 (
b11 *
b101 +
b1001 )
0"
#25000
b10100 e
b1010 d
1@
b1010 .
b1010 3"
b10100 -
b10100 2"
b10 7
b11 4
b1 8
b100000 <
b100000 u
b100000100000 ;
b100000100000 :
b10 *"
b11 +"
b10 6
b10 0"
b11 5
b11 1"
b1000 1
b1001010010000000100000 2
b1001010010000000100000 ,"
1_
b10000110000100000100000 f
b100 g
b1000 0
b100 m
b100 -"
1!
#30000
b1 #
0!
#35000
b101 e
b0 d
b0 .
b0 3"
b101 -
b101 2"
0H
b11110 I
b11110 t
b1100 1
b10001100000001100000000000000000 2
b10001100000001100000000000000000 ,"
b1 7
b101 4
b100 8
b10000000100000 ;
b10000000100000 :
b1 *"
b101 +"
b1 6
b1 0"
b101 5
b101 1"
b10100 K
b10100 s
b1010 J
b1010 q
b10100 M
b1010 L
b1100 0
b1000 m
b1000 -"
b1001010010000000100000 f
b1000 g
b1 ^
b11 b
b11 %"
b11 )"
b10 `
b10 $"
b100000100000 Y
b10100 c
b1010 a
b100 ]
1T
1!
#40000
b10 #
0!
#45000
b0 e
b100011 I
b100011 t
1B
1C
1E
1@
b0 -
b0 2"
1p
b10 >
b10 '"
b101 K
b101 s
b11110 J
b11110 q
b101 M
b11110 L
b100011 9
b100011 v
b0 7
b110 4
b0 8
b0 <
b0 u
b0 ;
b0 :
b0 *"
b110 +"
b0 6
b0 0"
b110 5
b110 1"
b10000 1
b110001010011100000100000 2
b110001010011100000100000 ,"
1l
b1 S
b1 #"
b10100 U
b10100 ~
b11110 N
b11110 }
b100 ^
b101 b
b101 %"
b101 )"
b1 `
b1 $"
b10000000100000 Y
b101 c
b0 a
b1000 ]
b10001100000001100000000000000000 f
b1100 g
b10000 0
b1100 m
b1100 -"
1!
#50000
b11 #
0!
#55000
b101 e
1H
b0 I
b0 t
0B
0C
0E
1@
b101 -
b101 2"
b10100 1
b10000010000110000000000000010 2
b10000010000110000000000000010 ,"
b0 9
b0 v
b110 7
b101 4
b111 8
b100000 <
b100000 u
b11100000100000 ;
b11100000100000 :
b110 *"
b101 +"
b110 6
b110 0"
b101 5
b101 1"
1G
03
0/
b0 >
b0 '"
b11110 o
b11110 /"
b1 n
b1 ."
b0 K
b0 s
b0 J
b0 q
b0 M
b0 L
b10100 0
b10000 m
b10000 -"
b110001010011100000100000 f
b10000 g
1[
1Z
1W
b110 ^
b110 b
b110 %"
b110 )"
b0 `
b0 $"
b0 Y
b0 c
b1100 ]
b100 S
b100 #"
b101 U
b101 ~
b100011 N
b100011 }
b1 j
b1 &"
b11110 h
1!
#60000
b100 #
0!
#65000
0H
b101 I
b101 t
b100011 o
b100011 /"
b100 n
b100 ."
b1100100 ?
b1100100 !"
0G
13
1/
b10 >
b10 '"
b101 K
b101 s
b101 M
b100 j
b100 &"
b100011 h
1Q
1P
b110 S
b110 #"
b0 U
b0 ~
b0 N
b0 }
0[
0Z
0W
0_
b111 ^
b101 b
b101 %"
b101 )"
b110 `
b110 $"
b11100000100000 Y
b101 c
b10000 ]
1!
#70000
b101 #
0!
#75000
b10100 e
b1010 d
b1 F
b1 |
1D
0@
b1010 .
b1010 3"
b10100 -
b10100 2"
b1101001 I
b1101001 t
b11000 1
b10000100100000000100000 2
b10000100100000000100000 ,"
b100 9
b100 v
b10 7
b11 4
b0 8
b10 <
b10 u
b10 ;
b10 :
b10 *"
b11 +"
b10 6
b10 0"
b11 5
b11 1"
b0 ?
b0 !"
b1 >
b1 '"
b1100100 o
b1100100 /"
b110 n
b110 ."
b1100100 J
b1100100 q
b1100100 L
b11000 0
b10100 m
b10100 -"
b10000010000110000000000000010 f
b10100 g
1_
0Q
0P
0T
b111 S
b111 #"
b101 U
b101 ~
b101 N
b101 }
1i
b110 j
b110 &"
b0 h
b1100100 k
1!
#80000
b110 #
0!
#85000
b1010 e
1@
b0 F
b0 |
0D
b1010 -
b1010 2"
b101 o
b101 /"
b111 n
b111 ."
0p
b11111111111111111111111111110110 I
b11111111111111111111111111110110 t
b0 >
b0 '"
b10100 K
b10100 s
b1010 J
b1010 q
b10100 M
b1010 L
b0 9
b0 v
b10 4
b1000 8
b100000 <
b100000 u
b100000000100000 ;
b100000000100000 :
b10 +"
b10 5
b10 1"
b11100 1
b11001010100100000100010 2
b11001010100100000100010 ,"
0i
0l
b111 j
b111 &"
b101 h
b0 k
1T
b1101001 N
b1101001 }
b1 V
b1 r
1X
0_
b11 ^
b11 b
b11 %"
b11 )"
b10 `
b10 $"
b10 Y
b10100 c
b1010 a
b10100 ]
b10000100100000000100000 f
b11000 g
b11100 0
b11000 m
b11000 -"
1!
#90000
b111 #
0!
